manim_onvoice/__init__.py
manim_onvoice/__main__.py
manim_onvoice/defaults.py
manim_onvoice/helper.py
manim_onvoice/modify_audio.py
manim_onvoice/tracker.py
manim_onvoice/voiceover_scene.py
manim_onvoice/services/__init__.py
manim_onvoice/services/base.py
manim_onvoice/services/recorder/__init__.py
manim_onvoice/services/recorder/utility.py
manim_onvoice-1.0.0.dist-info/LICENSE
manim_onvoice-1.0.0.dist-info/WHEEL
manim_onvoice-1.0.0.dist-info/METADATA
manim_onvoice-1.0.0.dist-info/RECORD
