Metadata-Version: 2.1
Name: manim_onvoice
Version: 1.0.0
Summary: Manim Onvoice Termux for Manim
Keywords: recorder,manim,termux
Author-email: AvN Learn <avnlearn@gmail.com>
Classifier: Programming Language :: Python :: 3
Classifier: License :: OSI Approved :: MIT License
Requires-Dist: manim
Requires-Dist: python-slugify
Requires-Dist: sox
Requires-Dist: mutagen
Requires-Dist: pydub
Project-URL: Home, https://github.com/avnlearn/manim-onvoice-termux.git
